cheez_semg_pico/__init__.py
cheez_semg_pico/port_manager.py
cheez_semg_pico/serial_decoder.py
cheez_semg_pico-1.0.0.dist-info/METADATA
cheez_semg_pico-1.0.0.dist-info/WHEEL
cheez_semg_pico-1.0.0.dist-info/top_level.txt
cheez_semg_pico-1.0.0.dist-info/RECORD
