Metadata-Version: 2.1
Name: cheez-semg-pico
Version: 1.0.0
Summary: SDK for CheezPico USB/BLE Devices
Author: Cheez
Classifier: Development Status :: 3 - Alpha
Classifier: Intended Audience :: Developers
Classifier: License :: OSI Approved :: MIT License
Classifier: Programming Language :: Python :: 3.7
Classifier: Programming Language :: Python :: 3.8
Classifier: Programming Language :: Python :: 3.9
Requires-Python: >=3.7
Requires-Dist: pyserial
Requires-Dist: aioserial
